geopyspark/__init__.py
geopyspark/__main__.py
geopyspark/geopyspark_constants.py
geopyspark/geopyspark_utils.py
geopyspark/command/__init__.py
geopyspark/command/configuration.py
geopyspark/geotools/__init__.py
geopyspark/geotools/geotools_protobufcodecs.py
geopyspark/geotools/shapefile.py
geopyspark/geotools/protobuf/__init__.py
geopyspark/geotools/protobuf/simpleFeatureMessages_pb2.py
geopyspark/geotrellis/__init__.py
geopyspark/geotrellis/catalog.py
geopyspark/geotrellis/color.py
geopyspark/geotrellis/combine_bands.py
geopyspark/geotrellis/constants.py
geopyspark/geotrellis/converters.py
geopyspark/geotrellis/cost_distance.py
geopyspark/geotrellis/euclidean_distance.py
geopyspark/geotrellis/geotiff.py
geopyspark/geotrellis/hillshade.py
geopyspark/geotrellis/histogram.py
geopyspark/geotrellis/key_conversion.py
geopyspark/geotrellis/layer.py
geopyspark/geotrellis/neighborhood.py
geopyspark/geotrellis/protobufcodecs.py
geopyspark/geotrellis/protobufserializer.py
geopyspark/geotrellis/rasterio.py
geopyspark/geotrellis/rasterize.py
geopyspark/geotrellis/s3.py
geopyspark/geotrellis/tms.py
geopyspark/geotrellis/union.py
geopyspark/geotrellis/protobuf/__init__.py
geopyspark/geotrellis/protobuf/extentMessages_pb2.py
geopyspark/geotrellis/protobuf/featureMessages_pb2.py
geopyspark/geotrellis/protobuf/keyMessages_pb2.py
geopyspark/geotrellis/protobuf/tileMessages_pb2.py
geopyspark/geotrellis/protobuf/tupleMessages_pb2.py
geopyspark/jars/__init__.py
geopyspark/vector_pipe/__init__.py
geopyspark/vector_pipe/features_collection.py
geopyspark/vector_pipe/osm_reader.py
geopyspark/vector_pipe/vector_pipe_protobufcodecs.py
geopyspark/vector_pipe/protobuf/__init__.py
geopyspark/vector_pipe/protobuf/featureMessages_pb2.py
geopyspark-0.4.3.dist-info/LICENSE.txt
geopyspark-0.4.3.dist-info/METADATA
geopyspark-0.4.3.dist-info/RECORD
geopyspark-0.4.3.dist-info/WHEEL
geopyspark-0.4.3.dist-info/entry_points.txt
geopyspark-0.4.3.dist-info/top_level.txt
