Metadata-Version: 2.1
Name: geopyspark
Version: 0.4.3
Summary: Python bindings for GeoTrellis
Home-page: UNKNOWN
Author: Jacob Bouffard, James McClain
Author-email: jbouffard@azavea.com, jmcclain@azavea.com
License: LICENSE
Download-URL: http://github.com/locationtech-labs/geopyspark
Platform: UNKNOWN
Classifier: Development Status :: 4 - Beta
Classifier: License :: OSI Approved :: Apache Software License
Classifier: Topic :: Scientific/Engineering
Classifier: Topic :: Scientific/Engineering :: GIS
Classifier: Topic :: Scientific/Engineering :: Information Analysis
Classifier: Programming Language :: Python :: 3.3
Classifier: Programming Language :: Python :: 3.4
Classifier: Programming Language :: Python :: 3.5
Classifier: Programming Language :: Python :: 3.6
Requires-Dist: protobuf (>=3.3.0)
Requires-Dist: numpy (>=1.8)
Requires-Dist: shapely (>=1.6b3)
Requires-Dist: pytz
Requires-Dist: python-dateutil (>=2.6.1)
